symbl_rest/__init__.py
symbl_rest/api_client.py
symbl_rest/configuration.py
symbl_rest/rest.py
symbl_rest/api/__init__.py
symbl_rest/api/action_items_api.py
symbl_rest/api/analytics_api.py
symbl_rest/api/async_api.py
symbl_rest/api/authentication_api.py
symbl_rest/api/call_score_api.py
symbl_rest/api/connection_to_endpoint_api.py
symbl_rest/api/conversation_data_api.py
symbl_rest/api/conversations_api.py
symbl_rest/api/entities_api.py
symbl_rest/api/experience_api.py
symbl_rest/api/external_event_web_hook_api.py
symbl_rest/api/follow_ups_api.py
symbl_rest/api/insights_api.py
symbl_rest/api/intents_api.py
symbl_rest/api/jobs_api.py
symbl_rest/api/members_api.py
symbl_rest/api/messages_api.py
symbl_rest/api/metric_api.py
symbl_rest/api/metric_entry_api.py
symbl_rest/api/put_members_information_api.py
symbl_rest/api/put_speaker_events_api.py
symbl_rest/api/questions_api.py
symbl_rest/api/topics_api.py
symbl_rest/api/trackers_api.py
symbl_rest/models/__init__.py
symbl_rest/models/action.py
symbl_rest/models/action_item_list_response.py
symbl_rest/models/analytics_list_response.py
symbl_rest/models/analytics_members_info.py
symbl_rest/models/analytics_members_info_overlap.py
symbl_rest/models/analytics_members_info_overlap_overlapping_members.py
symbl_rest/models/analytics_members_info_pace.py
symbl_rest/models/analytics_members_info_talk_time.py
symbl_rest/models/analytics_metrics_info.py
symbl_rest/models/async_audio_url_parameters.py
symbl_rest/models/async_confidence_threshold.py
symbl_rest/models/async_detect_phrases.py
symbl_rest/models/async_enable_all_trackers.py
symbl_rest/models/async_entities_payload.py
symbl_rest/models/async_meeting_name.py
symbl_rest/models/async_messages_field.py
symbl_rest/models/async_messages_field_inner.py
symbl_rest/models/async_response.py
symbl_rest/models/async_text_parameters.py
symbl_rest/models/async_trackers.py
symbl_rest/models/async_trackers_inner.py
symbl_rest/models/async_video_url_parameters.py
symbl_rest-1.0.14.dist-info/METADATA
symbl_rest-1.0.14.dist-info/WHEEL
symbl_rest-1.0.14.dist-info/top_level.txt
symbl_rest-1.0.14.dist-info/RECORD
