Metadata-Version: 2.1
Name: symbl-rest
Version: 1.0.14
Summary: symbl.ai APIs
Home-page: 
Author-email: info@symbl.ai
Keywords: Swagger,symbl.ai APIs
Requires-Dist: urllib3 >=1.15
Requires-Dist: six >=1.10
Requires-Dist: certifi
Requires-Dist: python-dateutil
